markdown_to_mongodb
