Metadata-Version: 1.0
Name: markdown-to-mongodb
Version: 0.1.3
Summary: ===================
